[
    {
        "co_owners": null,
        "keepers": null,
        "league_id": "1131190923725221888",
        "metadata": {
            "record": "WWWLWWLLWWWW",
            "streak": "4W"
        },
        "owner_id": "454375196476829696",
        "player_map": null,
        "players": [
            "11584",
            "11604",
            "3321",
            "4881",
            "6806",
            "6819",
            "8112",
            "8121",
            "8151",
            "8167",
            "8205",
            "8259",
            "9508",
            "9997",
            "BUF",
            "KC"
        ],
        "reserve": [
            "8205"
        ],
        "roster_id": 1,
        "settings": {
            "fpts": 1529,
            "fpts_against": 1315,
            "fpts_against_decimal": 72,
            "fpts_decimal": 72,
            "locked": 0,
            "losses": 3,
            "ppts": 1649,
            "ppts_decimal": 82,
            "ties": 0,
            "total_moves": 0,
            "waiver_budget_used": 68,
            "waiver_position": 9,
            "wins": 9
        },
        "starters": [
            "4881",
            "8151",
            "6806",
            "8112",
            "3321",
            "11604",
            "11584",
            "8259",
            "KC"
        ],
        "taxi": null
    },
    {
        "co_owners": null,
        "keepers": null,
        "league_id": "1131190923725221888",
        "metadata": {
            "record": "LWWWWWWWWWWL",
            "streak": "1L"
        },
        "owner_id": "477969841718816768",
        "player_map": null,
        "players": [
            "10235",
            "10871",
            "10937",
            "3198",
            "5850",
            "5927",
            "6904",
            "7525",
            "7547",
            "8110",
            "8132",
            "9500",
            "9754",
            "9756",
            "TB"
        ],
        "reserve": null,
        "roster_id": 2,
        "settings": {
            "fpts": 1536,
            "fpts_against": 1358,
            "fpts_against_decimal": 36,
            "fpts_decimal": 18,
            "locked": 0,
            "losses": 2,
            "ppts": 1673,
            "ppts_decimal": 18,
            "ties": 0,
            "total_moves": 0,
            "waiver_budget_used": 100,
            "waiver_position": 12,
            "wins": 10
        },
        "starters": [
            "6904",
            "3198",
            "5850",
            "7547",
            "5927",
            "10871",
            "9500",
            "10937",
            "TB"
        ],
        "taxi": null
    },
    {
        "co_owners": null,
        "keepers": null,
        "league_id": "1131190923725221888",
        "metadata": {
            "record": "WWWLLWLLLLLW",
            "streak": "1W"
        },
        "owner_id": "731510990612578304",
        "player_map": null,
        "players": [
            "10222",
            "10229",
            "10236",
            "11533",
            "11576",
            "4066",
            "4983",
            "7569",
            "7594",
            "7670",
            "8155",
            "9226",
            "9484",
            "9753",
            "9758",
            "CLE"
        ],
        "reserve": [
            "10229"
        ],
        "roster_id": 3,
        "settings": {
            "fpts": 1324,
            "fpts_against": 1387,
            "fpts_against_decimal": 42,
            "fpts_decimal": 60,
            "locked": 0,
            "losses": 7,
            "ppts": 1568,
            "ppts_decimal": 40,
            "ties": 0,
            "total_moves": 0,
            "waiver_budget_used": 38,
            "waiver_position": 10,
            "wins": 5
        },
        "starters": [
            "9758",
            "9226",
            "7594",
            "4983",
            "10222",
            "9484",
            "7569",
            "11533",
            "CLE"
        ],
        "taxi": null
    },
    {
        "co_owners": null,
        "keepers": null,
        "league_id": "1131190923725221888",
        "metadata": {
            "allow_pn_inactive_starters": "on",
            "allow_pn_player_injury_status": "on",
            "allow_pn_scoring": "on",
            "record": "WLWLLWWLLLWW",
            "restrict_pn_scoring_starters_only": "on",
            "streak": "2W"
        },
        "owner_id": "454264054911856640",
        "player_map": null,
        "players": [
            "11638",
            "1479",
            "1945",
            "2309",
            "4018",
            "4984",
            "5022",
            "5844",
            "5859",
            "7021",
            "7571",
            "8150",
            "8228",
            "9229",
            "HOU"
        ],
        "reserve": null,
        "roster_id": 4,
        "settings": {
            "fpts": 1425,
            "fpts_against": 1463,
            "fpts_against_decimal": 92,
            "fpts_decimal": 80,
            "locked": 0,
            "losses": 6,
            "ppts": 1544,
            "ppts_decimal": 80,
            "ties": 0,
            "total_moves": 0,
            "waiver_budget_used": 85,
            "waiver_position": 11,
            "wins": 6
        },
        "starters": [
            "9229",
            "4018",
            "8150",
            "1479",
            "5859",
            "5022",
            "7571",
            "1945",
            "HOU"
        ],
        "taxi": null
    },
    {
        "co_owners": null,
        "keepers": null,
        "league_id": "1131190923725221888",
        "metadata": {
            "record": "WLLLWLWWLWWW",
            "streak": "3W"
        },
        "owner_id": "784502790046261248",
        "player_map": null,
        "players": [
            "11539",
            "11583",
            "2216",
            "4663",
            "4892",
            "4981",
            "5010",
            "5086",
            "6790",
            "6797",
            "7553",
            "7611",
            "8136",
            "8137",
            "8144",
            "MIA"
        ],
        "reserve": [
            "8144"
        ],
        "roster_id": 5,
        "settings": {
            "fpts": 1242,
            "fpts_against": 1257,
            "fpts_against_decimal": 58,
            "fpts_decimal": 92,
            "locked": 0,
            "losses": 5,
            "ppts": 1475,
            "ppts_decimal": 60,
            "ties": 0,
            "total_moves": 0,
            "waiver_budget_used": 67,
            "waiver_position": 8,
            "wins": 7
        },
        "starters": [
            "6797",
            "7611",
            "6790",
            "4981",
            "8137",
            "5010",
            "2216",
            "11539",
            "MIA"
        ],
        "taxi": null
    },
    {
        "co_owners": null,
        "keepers": null,
        "league_id": "1131190923725221888",
        "metadata": {
            "record": "LWLLLWLLWLLL",
            "streak": "3L"
        },
        "owner_id": "389893330558828544",
        "player_map": null,
        "players": [
            "10859",
            "11563",
            "1264",
            "1339",
            "3163",
            "3214",
            "5892",
            "6813",
            "8111",
            "8134",
            "8146",
            "9224",
            "9488",
            "9501",
            "BAL"
        ],
        "reserve": null,
        "roster_id": 6,
        "settings": {
            "fpts": 1284,
            "fpts_against": 1416,
            "fpts_against_decimal": 88,
            "fpts_decimal": 44,
            "locked": 0,
            "losses": 9,
            "ppts": 1493,
            "ppts_decimal": 80,
            "ties": 0,
            "total_moves": 0,
            "waiver_budget_used": 89,
            "waiver_position": 2,
            "wins": 3
        },
        "starters": [
            "11563",
            "6813",
            "5892",
            "9488",
            "9501",
            "8111",
            "1339",
            "1264",
            "BAL"
        ],
        "taxi": null
    },
    {
        "co_owners": null,
        "keepers": null,
        "league_id": "1131190923725221888",
        "metadata": {
            "allow_pn_inactive_starters": "off",
            "allow_pn_player_injury_status": "off",
            "allow_pn_scoring": "off",
            "record": "LLWWLWLWWWLL",
            "restrict_pn_scoring_starters_only": "on",
            "streak": "2L"
        },
        "owner_id": "990515534686945280",
        "player_map": null,
        "players": [
            "1466",
            "2747",
            "4046",
            "4137",
            "4199",
            "4381",
            "4666",
            "5045",
            "5947",
            "5987",
            "6768",
            "6794",
            "7049",
            "PHI",
            "SF"
        ],
        "reserve": null,
        "roster_id": 7,
        "settings": {
            "fpts": 1309,
            "fpts_against": 1488,
            "fpts_against_decimal": 28,
            "fpts_decimal": 4,
            "locked": 0,
            "losses": 6,
            "ppts": 1528,
            "ppts_decimal": 20,
            "ties": 0,
            "total_moves": 0,
            "waiver_budget_used": 69,
            "waiver_position": 5,
            "wins": 6
        },
        "starters": [
            "4046",
            "4199",
            "4137",
            "5045",
            "6794",
            "1466",
            "7049",
            "2747",
            "SF"
        ],
        "taxi": null
    },
    {
        "co_owners": null,
        "keepers": null,
        "league_id": "1131190923725221888",
        "metadata": {
            "record": "WLWWWLLWWLLW",
            "streak": "1W"
        },
        "owner_id": "733736339916337152",
        "player_map": null,
        "players": [
            "11560",
            "11620",
            "11628",
            "1426",
            "2306",
            "2374",
            "2449",
            "4035",
            "4098",
            "4195",
            "4217",
            "4866",
            "4988",
            "5967",
            "8183",
            "LAC"
        ],
        "reserve": [
            "2449"
        ],
        "roster_id": 8,
        "settings": {
            "fpts": 1599,
            "fpts_against": 1295,
            "fpts_against_decimal": 74,
            "fpts_decimal": 74,
            "locked": 0,
            "losses": 5,
            "ppts": 1747,
            "ppts_decimal": 18,
            "ties": 0,
            "total_moves": 0,
            "waiver_budget_used": 29,
            "waiver_position": 1,
            "wins": 7
        },
        "starters": [
            "11560",
            "4866",
            "4035",
            "11628",
            "1426",
            "4217",
            "5967",
            "4195",
            "LAC"
        ],
        "taxi": null
    },
    {
        "co_owners": null,
        "keepers": null,
        "league_id": "1131190923725221888",
        "metadata": {
            "record": "LLLWLLLLLLLL",
            "streak": "8L"
        },
        "owner_id": "685160227418492928",
        "player_map": null,
        "players": [
            "11624",
            "1166",
            "1433",
            "3286",
            "4034",
            "4227",
            "5001",
            "5012",
            "5995",
            "6786",
            "6804",
            "8126",
            "8143",
            "8676",
            "9225",
            "9504",
            "DET"
        ],
        "reserve": [
            "4227",
            "8676"
        ],
        "roster_id": 9,
        "settings": {
            "fpts": 1057,
            "fpts_against": 1505,
            "fpts_against_decimal": 40,
            "fpts_decimal": 8,
            "locked": 0,
            "losses": 11,
            "ppts": 1322,
            "ppts_decimal": 64,
            "ties": 0,
            "total_moves": 0,
            "waiver_budget_used": 96,
            "waiver_position": 3,
            "wins": 1
        },
        "starters": [
            "6804",
            "8143",
            "4034",
            "6786",
            "11624",
            "5001",
            "5012",
            "1433",
            "DET"
        ],
        "taxi": null
    },
    {
        "co_owners": null,
        "keepers": null,
        "league_id": "1131190923725221888",
        "metadata": {
            "allow_pn_inactive_starters": "on",
            "allow_pn_player_injury_status": "on",
            "allow_pn_scoring": "off",
            "record": "LWLLLLWWWWLL",
            "restrict_pn_scoring_starters_only": "on",
            "streak": "2L"
        },
        "owner_id": "700017402770968576",
        "player_map": null,
        "players": [
            "11632",
            "11635",
            "1234",
            "2133",
            "4033",
            "5119",
            "5846",
            "5849",
            "6783",
            "6938",
            "7588",
            "8138",
            "8148",
            "9509",
            "DEN"
        ],
        "reserve": null,
        "roster_id": 10,
        "settings": {
            "fpts": 1351,
            "fpts_against": 1429,
            "fpts_against_decimal": 60,
            "fpts_decimal": 82,
            "locked": 0,
            "losses": 7,
            "ppts": 1533,
            "ppts_decimal": 2,
            "ties": 0,
            "total_moves": 0,
            "waiver_budget_used": 26,
            "waiver_position": 4,
            "wins": 5
        },
        "starters": [
            "5849",
            "9509",
            "8138",
            "5846",
            "8148",
            "4033",
            "11635",
            "5119",
            "DEN"
        ],
        "taxi": null
    },
    {
        "co_owners": null,
        "keepers": null,
        "league_id": "1131190923725221888",
        "metadata": {
            "record": "LLLWWLWLLWWL",
            "streak": "1L"
        },
        "owner_id": "568840665636675584",
        "player_map": null,
        "players": [
            "11579",
            "11631",
            "11655",
            "12185",
            "1373",
            "1689",
            "5872",
            "6770",
            "7564",
            "8130",
            "8154",
            "9493",
            "9502",
            "MIN",
            "WAS"
        ],
        "reserve": null,
        "roster_id": 11,
        "settings": {
            "fpts": 1425,
            "fpts_against": 1395,
            "fpts_against_decimal": 64,
            "fpts_decimal": 18,
            "locked": 0,
            "losses": 7,
            "ppts": 1547,
            "ppts_decimal": 38,
            "ties": 0,
            "total_moves": 0,
            "waiver_budget_used": 55,
            "waiver_position": 7,
            "wins": 5
        },
        "starters": [
            "1373",
            "11655",
            "8154",
            "9502",
            "5872",
            "8130",
            "9493",
            "12185",
            "WAS"
        ],
        "taxi": null
    },
    {
        "co_owners": null,
        "keepers": null,
        "league_id": "1131190923725221888",
        "metadata": {
            "record": "WWLWWLWWLLWW",
            "streak": "2W"
        },
        "owner_id": "737323708410138624",
        "player_map": null,
        "players": [
            "10444",
            "11566",
            "3451",
            "4037",
            "4039",
            "4144",
            "4943",
            "5248",
            "6801",
            "7090",
            "7526",
            "7528",
            "7543",
            "8142",
            "9221",
            "PIT"
        ],
        "reserve": [
            "4037"
        ],
        "roster_id": 12,
        "settings": {
            "fpts": 1467,
            "fpts_against": 1239,
            "fpts_against_decimal": 6,
            "fpts_decimal": 8,
            "locked": 0,
            "losses": 4,
            "ppts": 1644,
            "ppts_decimal": 32,
            "ties": 0,
            "total_moves": 0,
            "waiver_budget_used": 100,
            "waiver_position": 6,
            "wins": 8
        },
        "starters": [
            "11566",
            "9221",
            "7528",
            "7526",
            "4039",
            "4144",
            "10444",
            "3451",
            "PIT"
        ],
        "taxi": null
    }
]