[
    {
        "co_owners": null,
        "keepers": null,
        "league_id": "1127629772399456256",
        "metadata": {
            "allow_pn_inactive_starters": "on",
            "allow_pn_player_injury_status": "on",
            "allow_pn_scoring": "off",
            "record": "WLWLLWLWLWLWL",
            "restrict_pn_scoring_starters_only": "on",
            "streak": "1L"
        },
        "owner_id": "858214091569893376",
        "player_map": null,
        "players": [
            "10859",
            "1234",
            "1339",
            "2020",
            "4098",
            "4199",
            "6786",
            "6904",
            "7528",
            "8126",
            "8148",
            "8154",
            "9493",
            "9502",
            "TB"
        ],
        "reserve": null,
        "roster_id": 1,
        "settings": {
            "fpts": 1397,
            "fpts_against": 1531,
            "fpts_against_decimal": 8,
            "fpts_decimal": 60,
            "losses": 7,
            "ppts": 1665,
            "ppts_decimal": 98,
            "ties": 0,
            "total_moves": 0,
            "waiver_budget_used": 94,
            "waiver_position": 4,
            "wins": 6
        },
        "starters": [
            "6904",
            "4199",
            "8154",
            "6786",
            "8148",
            "1339",
            "9493",
            "2020",
            "TB"
        ],
        "taxi": null
    },
    {
        "co_owners": null,
        "keepers": null,
        "league_id": "1127629772399456256",
        "metadata": {
            "record": "WWWLLLWWWWLWW",
            "streak": "2W"
        },
        "owner_id": "832545337607557120",
        "player_map": null,
        "players": [
            "11583",
            "11632",
            "1479",
            "4195",
            "4881",
            "4943",
            "6130",
            "6794",
            "7525",
            "7600",
            "8130",
            "8228",
            "9226",
            "9756",
            "MIN"
        ],
        "reserve": null,
        "roster_id": 2,
        "settings": {
            "fpts": 1661,
            "fpts_against": 1429,
            "fpts_against_decimal": 76,
            "fpts_decimal": 68,
            "losses": 4,
            "ppts": 1767,
            "ppts_decimal": 74,
            "ties": 0,
            "total_moves": 0,
            "waiver_budget_used": 50,
            "waiver_position": 9,
            "wins": 9
        },
        "starters": [
            "4881",
            "8228",
            "9226",
            "6794",
            "11632",
            "8130",
            "1479",
            "4195",
            "MIN"
        ],
        "taxi": null
    },
    {
        "co_owners": null,
        "keepers": null,
        "league_id": "1127629772399456256",
        "metadata": {
            "record": "WWLWLWWWWWWWW",
            "streak": "8W"
        },
        "owner_id": "843052328373301248",
        "player_map": null,
        "players": [
            "11563",
            "11584",
            "11624",
            "2133",
            "3451",
            "4033",
            "4892",
            "5859",
            "5967",
            "7594",
            "8136",
            "8138",
            "9754",
            "ARI",
            "PHI"
        ],
        "reserve": null,
        "roster_id": 3,
        "settings": {
            "fpts": 1546,
            "fpts_against": 1322,
            "fpts_against_decimal": 52,
            "fpts_decimal": 16,
            "losses": 2,
            "ppts": 1747,
            "ppts_decimal": 50,
            "ties": 0,
            "total_moves": 0,
            "waiver_budget_used": 78,
            "waiver_position": 5,
            "wins": 11
        },
        "starters": [
            "4892",
            "7594",
            "11584",
            "2133",
            "5859",
            "4033",
            "8138",
            "3451",
            "ARI"
        ],
        "taxi": null
    },
    {
        "co_owners": null,
        "keepers": null,
        "league_id": "1127629772399456256",
        "metadata": {
            "allow_pn_inactive_starters": "on",
            "allow_pn_player_injury_status": "on",
            "allow_pn_scoring": "on",
            "record": "LWWWWLLLWWWLW",
            "restrict_pn_scoring_starters_only": "on",
            "streak": "1W"
        },
        "owner_id": "1120108718089244672",
        "player_map": null,
        "players": [
            "10229",
            "11533",
            "11560",
            "11566",
            "4066",
            "4988",
            "5012",
            "5947",
            "6813",
            "7526",
            "7547",
            "8151",
            "9500",
            "9753",
            "IND",
            "PIT"
        ],
        "reserve": [
            "10229"
        ],
        "roster_id": 4,
        "settings": {
            "fpts": 1458,
            "fpts_against": 1515,
            "fpts_against_decimal": 14,
            "fpts_decimal": 60,
            "losses": 5,
            "ppts": 1670,
            "ppts_decimal": 76,
            "ties": 0,
            "total_moves": 0,
            "waiver_budget_used": 98,
            "waiver_position": 6,
            "wins": 8
        },
        "starters": [
            "11566",
            "8151",
            "6813",
            "7547",
            "7526",
            "4066",
            "5947",
            "11533",
            "IND"
        ],
        "taxi": null
    },
    {
        "co_owners": null,
        "keepers": null,
        "league_id": "1127629772399456256",
        "metadata": {
            "record": "LLWLLLWLWLWLL",
            "streak": "2L"
        },
        "owner_id": "848687558241157120",
        "player_map": null,
        "players": [
            "10444",
            "11620",
            "11637",
            "1373",
            "1426",
            "2216",
            "4018",
            "4666",
            "5022",
            "6801",
            "8111",
            "8121",
            "8150",
            "9229",
            "HOU"
        ],
        "reserve": null,
        "roster_id": 5,
        "settings": {
            "fpts": 1497,
            "fpts_against": 1593,
            "fpts_against_decimal": 12,
            "fpts_decimal": 58,
            "losses": 9,
            "ppts": 1632,
            "ppts_decimal": 26,
            "ties": 0,
            "total_moves": 0,
            "waiver_budget_used": 100,
            "waiver_position": 10,
            "wins": 4
        },
        "starters": [
            "1373",
            "4018",
            "8150",
            "6801",
            "2216",
            "8111",
            "1426",
            "4666",
            "HOU"
        ],
        "taxi": null
    },
    {
        "co_owners": null,
        "keepers": null,
        "league_id": "1127629772399456256",
        "metadata": {
            "record": "WWWLWWWWLWWWW",
            "streak": "4W"
        },
        "owner_id": "859682536320778240",
        "player_map": null,
        "players": [
            "11604",
            "4035",
            "4037",
            "421",
            "4866",
            "4983",
            "5927",
            "6650",
            "6768",
            "6826",
            "7567",
            "8134",
            "8183",
            "9221",
            "DAL",
            "MIA"
        ],
        "reserve": [
            "4037"
        ],
        "roster_id": 6,
        "settings": {
            "fpts": 1851,
            "fpts_against": 1411,
            "fpts_against_decimal": 86,
            "fpts_decimal": 72,
            "losses": 2,
            "ppts": 2012,
            "ppts_decimal": 66,
            "ties": 0,
            "total_moves": 0,
            "waiver_budget_used": 28,
            "waiver_position": 12,
            "wins": 11
        },
        "starters": [
            "421",
            "4035",
            "9221",
            "5927",
            "4983",
            "11604",
            "4866",
            "6650",
            "DAL"
        ],
        "taxi": null
    },
    {
        "co_owners": null,
        "keepers": null,
        "league_id": "1127629772399456256",
        "metadata": {
            "record": "LWWWLWWWLLLLW",
            "streak": "1W"
        },
        "owner_id": "469622629356007424",
        "player_map": null,
        "players": [
            "10937",
            "11626",
            "11628",
            "3163",
            "4046",
            "4144",
            "4217",
            "5937",
            "6783",
            "6790",
            "7569",
            "7588",
            "8408",
            "9509",
            "KC"
        ],
        "reserve": null,
        "roster_id": 7,
        "settings": {
            "fpts": 1516,
            "fpts_against": 1481,
            "fpts_against_decimal": 32,
            "fpts_decimal": 36,
            "losses": 6,
            "ppts": 1772,
            "ppts_decimal": 32,
            "ties": 0,
            "total_moves": 0,
            "waiver_budget_used": 56,
            "waiver_position": 3,
            "wins": 7
        },
        "starters": [
            "4046",
            "9509",
            "7588",
            "7569",
            "6783",
            "4217",
            "11628",
            "10937",
            "KC"
        ],
        "taxi": null
    },
    {
        "co_owners": null,
        "keepers": null,
        "league_id": "1127629772399456256",
        "metadata": {
            "record": "WLLLWWLWLLLWL",
            "streak": "1L"
        },
        "owner_id": "831982165393784832",
        "player_map": null,
        "players": [
            "10222",
            "11581",
            "1466",
            "2449",
            "3321",
            "4029",
            "4663",
            "5850",
            "6820",
            "8131",
            "8230",
            "8259",
            "96",
            "9758",
            "9997",
            "GB",
            "WAS"
        ],
        "reserve": [
            "2449",
            "4663"
        ],
        "roster_id": 8,
        "settings": {
            "fpts": 1430,
            "fpts_against": 1591,
            "fpts_against_decimal": 64,
            "fpts_decimal": 10,
            "losses": 8,
            "ppts": 1564,
            "ppts_decimal": 10,
            "ties": 0,
            "total_moves": 0,
            "waiver_budget_used": 16,
            "waiver_position": 2,
            "wins": 5
        },
        "starters": [
            "9758",
            "5850",
            "8230",
            "3321",
            "9997",
            "1466",
            "10222",
            "8259",
            "GB"
        ],
        "taxi": null
    },
    {
        "co_owners": null,
        "keepers": null,
        "league_id": "1127629772399456256",
        "metadata": {
            "record": "LWLWWLLLLLLLW",
            "streak": "1W"
        },
        "owner_id": "604766888475578368",
        "player_map": null,
        "players": [
            "10235",
            "11592",
            "11655",
            "1945",
            "2309",
            "2749",
            "3214",
            "3286",
            "5872",
            "6797",
            "6804",
            "7496",
            "7611",
            "8112",
            "8155",
            "8676",
            "DET"
        ],
        "reserve": [
            "11592",
            "8676"
        ],
        "roster_id": 9,
        "settings": {
            "fpts": 1290,
            "fpts_against": 1452,
            "fpts_against_decimal": 84,
            "fpts_decimal": 46,
            "losses": 9,
            "ppts": 1552,
            "ppts_decimal": 56,
            "ties": 0,
            "total_moves": 0,
            "waiver_budget_used": 37,
            "waiver_position": 7,
            "wins": 4
        },
        "starters": [
            "6797",
            "7611",
            "11655",
            "7496",
            "8112",
            "3214",
            "8155",
            "1945",
            "DET"
        ],
        "taxi": null
    },
    {
        "co_owners": null,
        "keepers": null,
        "league_id": "1127629772399456256",
        "metadata": {
            "record": "WLLWLWLLWLWWL",
            "streak": "1L"
        },
        "owner_id": "869953012045656064",
        "player_map": null,
        "players": [
            "4034",
            "4227",
            "4984",
            "5045",
            "5119",
            "5248",
            "5844",
            "5892",
            "6806",
            "8110",
            "8137",
            "8146",
            "9225",
            "9484",
            "9488",
            "NYJ"
        ],
        "reserve": [
            "4227"
        ],
        "roster_id": 10,
        "settings": {
            "fpts": 1531,
            "fpts_against": 1458,
            "fpts_against_decimal": 6,
            "fpts_decimal": 66,
            "losses": 7,
            "ppts": 1720,
            "ppts_decimal": 28,
            "ties": 0,
            "total_moves": 0,
            "waiver_budget_used": 76,
            "waiver_position": 11,
            "wins": 6
        },
        "starters": [
            "4984",
            "5248",
            "5892",
            "9488",
            "8137",
            "5844",
            "8146",
            "5119",
            "NYJ"
        ],
        "taxi": null
    },
    {
        "co_owners": null,
        "keepers": null,
        "league_id": "1127629772399456256",
        "metadata": {
            "record": "LLLWWLWLLLLLL",
            "streak": "6L"
        },
        "owner_id": "1130510866379796480",
        "player_map": null,
        "players": [
            "10236",
            "11539",
            "11631",
            "3198",
            "4039",
            "4381",
            "4981",
            "5846",
            "5849",
            "7049",
            "7090",
            "7523",
            "7543",
            "9224",
            "BAL"
        ],
        "reserve": null,
        "roster_id": 11,
        "settings": {
            "fpts": 1282,
            "fpts_against": 1611,
            "fpts_against_decimal": 64,
            "fpts_decimal": 82,
            "losses": 10,
            "ppts": 1668,
            "ppts_decimal": 50,
            "ties": 0,
            "total_moves": 0,
            "waiver_budget_used": 45,
            "waiver_position": 1,
            "wins": 3
        },
        "starters": [
            "5849",
            "7543",
            "3198",
            "5846",
            "7090",
            "10236",
            "4039",
            "11539",
            "BAL"
        ],
        "taxi": null
    },
    {
        "co_owners": null,
        "keepers": null,
        "league_id": "1127629772399456256",
        "metadata": {
            "record": "LLLLWLLLWWWLL",
            "streak": "2L"
        },
        "owner_id": "1126497587315470336",
        "player_map": null,
        "players": [
            "11635",
            "1264",
            "4137",
            "5010",
            "5086",
            "6770",
            "6819",
            "6938",
            "7021",
            "7553",
            "7564",
            "8144",
            "8205",
            "9999",
            "BUF",
            "DEN"
        ],
        "reserve": [
            "8144"
        ],
        "roster_id": 12,
        "settings": {
            "fpts": 1528,
            "fpts_against": 1594,
            "fpts_against_decimal": 36,
            "fpts_decimal": 60,
            "losses": 9,
            "ppts": 1687,
            "ppts_decimal": 10,
            "ties": 0,
            "total_moves": 0,
            "waiver_budget_used": 0,
            "waiver_position": 8,
            "wins": 4
        },
        "starters": [
            "6770",
            "7021",
            "4137",
            "7564",
            "11635",
            "5010",
            "8205",
            "1264",
            "DEN"
        ],
        "taxi": null
    }
]